adjustText/__init__.py
adjustText/_version.py
adjustText/arrops.py
adjustText-1.1.0.dist-info/LICENSE
adjustText-1.1.0.dist-info/METADATA
adjustText-1.1.0.dist-info/WHEEL
adjustText-1.1.0.dist-info/top_level.txt
adjustText-1.1.0.dist-info/RECORD
