Metadata-Version: 2.1
Name: adjustText
Version: 1.1.0
Summary: Iteratively adjust text position in matplotlib plots to minimize overlaps
Home-page: https://github.com/Phlya/adjustText
Author: Ilya Flyamer
Author-email: flyamer@gmail.com
License: MIT
Project-URL: Documentation, https://adjusttext.readthedocs.io/
Classifier: Framework :: Matplotlib
Classifier: Topic :: Scientific/Engineering :: Visualization
License-File: LICENSE
Requires-Dist: numpy
Requires-Dist: matplotlib
Requires-Dist: scipy
